resource/ros2tree
ros2tree/__init__.py
ros2tree/api/__init__.py
ros2tree/api/tree_builder.py
ros2tree/api/tree_formatter.py
ros2tree/command/__init__.py
ros2tree/command/tree.py
ros2tree/verb/__init__.py
ros2tree/verb/all.py
ros2tree/verb/nodes.py
ros2tree/verb/services.py
ros2tree/verb/topics.py
ros2tree-0.2.0.data/data/share/ament_index/resource_index/packages/ros2tree
ros2tree-0.2.0.data/data/share/ros2tree/package.xml
ros2tree-0.2.0.dist-info/licenses/LICENSE
ros2tree-0.2.0.dist-info/METADATA
ros2tree-0.2.0.dist-info/WHEEL
ros2tree-0.2.0.dist-info/entry_points.txt
ros2tree-0.2.0.dist-info/top_level.txt
ros2tree-0.2.0.dist-info/zip-safe
ros2tree-0.2.0.dist-info/RECORD
