Metadata-Version: 2.4
Name: ros2tree
Version: 0.2.0
Summary: ROS2 command extension that displays topics, nodes, and services in a hierarchical tree format
Author: Lin Hsiang-Jui
Author-email: Lin Hsiang-Jui <jerry73204@gmail.com>
Maintainer: Lin Hsiang-Jui
Maintainer-email: Lin Hsiang-Jui <jerry73204@gmail.com>
License-Expression: Apache-2.0
Project-URL: Homepage, https://github.com/jerry73204/ros2tree
Project-URL: Bug Reports, https://github.com/jerry73204/ros2tree/issues
Project-URL: Source, https://github.com/jerry73204/ros2tree
Project-URL: Documentation, https://github.com/jerry73204/ros2tree#readme
Keywords: ros2,tree,visualization,topics,nodes,services,introspection
Classifier: Development Status :: 4 - Beta
Classifier: Intended Audience :: Developers
Classifier: Intended Audience :: Science/Research
Classifier: Operating System :: POSIX :: Linux
Classifier: Programming Language :: Python :: 3
Classifier: Programming Language :: Python :: 3.8
Classifier: Programming Language :: Python :: 3.9
Classifier: Programming Language :: Python :: 3.10
Classifier: Programming Language :: Python :: 3.11
Classifier: Programming Language :: Python :: 3.12
Classifier: Topic :: Scientific/Engineering
Classifier: Topic :: Software Development :: Libraries :: Python Modules
Classifier: Topic :: System :: Distributed Computing
Requires-Python: >=3.8
License-File: LICENSE
Requires-Dist: setuptools
Provides-Extra: dev
Requires-Dist: pytest; extra == "dev"
Requires-Dist: pytest-cov; extra == "dev"
Dynamic: author
Dynamic: license-file
Dynamic: maintainer
